{"data_mtime": 1678885104, "dep_lines": [7, 9, 1, 1, 1, 1, 1, 1, 1, 1, 1, 1, 1, 1, 1, 1, 1, 1, 20, 21, 23], "dep_prios": [5, 5, 5, 30, 30, 30, 30, 30, 30, 30, 30, 30, 30, 30, 30, 30, 30, 30, 5, 5, 5], "dependencies": ["typing", "numpy", "builtins", "abc", "numpy.core.fromnumeric", "numpy.core.numeric", "numpy.core.shape_base", "numpy.lib", "numpy.lib.arraysetops", "numpy.lib.function_base", "numpy.typing", "numpy.typing._array_like", "numpy.typing._dtype_like", "typing_extensions", "enum", "numpy.core", "numpy.core.multiarray", "numpy.typing._nested_sequence"], "hash": "1542bbe52af78d97b86f53afb5dd393a04c166615b98b5d5805d950d896973a8", "id": "src.statkit.non_parametric", "ignore_all": false, "interface_hash": "41f4a8a24bfa14b211581b2a28ca335a6d4496754246ee0ef7704b80b6873565", "mtime": 1677669991, "options": {"allow_redefinition": false, "allow_untyped_globals": false, "always_false": [], "always_true": [], "bazel": false, "check_untyped_defs": false, "disallow_any_decorated": false, "disallow_any_explicit": false, "disallow_any_expr": false, "disallow_any_generics": false, "disallow_any_unimported": false, "disallow_incomplete_defs": false, "disallow_subclassing_any": false, "disallow_untyped_calls": false, "disallow_untyped_decorators": false, "disallow_untyped_defs": false, "follow_imports": "silent", "follow_imports_for_stubs": false, "ignore_errors": false, "ignore_missing_imports": true, "implicit_reexport": true, "local_partial_types": false, "mypyc": false, "no_implicit_optional": false, "platform": "linux", "plugins": [], "show_none_errors": true, "strict_equality": false, "strict_optional": true, "strict_optional_whitelist": null, "warn_no_return": true, "warn_return_any": false, "warn_unreachable": false, "warn_unused_ignores": false}, "path": "/home/hylke/workspace/statkit/src/statkit/non_parametric.py", "plugin_data": null, "size": 8375, "suppressed": ["pandas", "sklearn.utils", "statkit.types"], "version_id": "0.942"}