{".class": "MypyFile", "_fullname": "watchdog.observers.read_directory_changes", "future_import_flags": [], "is_partial_stub_package": false, "is_stub": false, "names": {".class": "SymbolTable", "BaseObserver": {".class": "SymbolTableNode", "cross_ref": "watchdog.observers.api.BaseObserver", "kind": "Gdef"}, "DEFAULT_EMITTER_TIMEOUT": {".class": "SymbolTableNode", "cross_ref": "watchdog.observers.api.DEFAULT_EMITTER_TIMEOUT", "kind": "Gdef"}, "DEFAULT_OBSERVER_TIMEOUT": {".class": "SymbolTableNode", "cross_ref": "watchdog.observers.api.DEFAULT_OBSERVER_TIMEOUT", "kind": "Gdef"}, "DirCreatedEvent": {".class": "SymbolTableNode", "cross_ref": "watchdog.events.DirCreatedEvent", "kind": "Gdef"}, "DirDeletedEvent": {".class": "SymbolTableNode", "cross_ref": "watchdog.events.DirDeletedEvent", "kind": "Gdef"}, "DirModifiedEvent": {".class": "SymbolTableNode", "cross_ref": "watchdog.events.DirModifiedEvent", "kind": "Gdef"}, "DirMovedEvent": {".class": "SymbolTableNode", "cross_ref": "watchdog.events.DirMovedEvent", "kind": "Gdef"}, "EventEmitter": {".class": "SymbolTableNode", "cross_ref": "watchdog.observers.api.EventEmitter", "kind": "Gdef"}, "FileCreatedEvent": {".class": "SymbolTableNode", "cross_ref": "watchdog.events.FileCreatedEvent", "kind": "Gdef"}, "FileDeletedEvent": {".class": "SymbolTableNode", "cross_ref": "watchdog.events.FileDeletedEvent", "kind": "Gdef"}, "FileModifiedEvent": {".class": "SymbolTableNode", "cross_ref": "watchdog.events.FileModifiedEvent", "kind": "Gdef"}, "FileMovedEvent": {".class": "SymbolTableNode", "cross_ref": "watchdog.events.FileMovedEvent", "kind": "Gdef"}, "WATCHDOG_TRAVERSE_MOVED_DIR_DELAY": {".class": "SymbolTableNode", "kind": "Gdef", "node": {".class": "Var", "flags": ["is_ready", "is_inferred", "has_explicit_value"], "fullname": "watchdog.observers.read_directory_changes.WATCHDOG_TRAVERSE_MOVED_DIR_DELAY", "name": "WATCHDOG_TRAVERSE_MOVED_DIR_DELAY", "type": "builtins.int"}}, "WindowsApiEmitter": {".class": "SymbolTableNode", "kind": "Gdef", "node": {".class": "TypeInfo", "_promote": [], "abstract_attributes": [], "bases": ["watchdog.observers.api.EventEmitter"], "declared_metaclass": null, "defn": {".class": "ClassDef", "fullname": "watchdog.observers.read_directory_changes.WindowsApiEmitter", "name": "WindowsApiEmitter", "type_vars": []}, "deletable_attributes": [], "flags": [], "fullname": "watchdog.observers.read_directory_changes.WindowsApiEmitter", "has_param_spec_type": false, "metaclass_type": null, "metadata": {}, "module_name": "watchdog.observers.read_directory_changes", "mro": ["watchdog.observers.read_directory_changes.WindowsApiEmitter", "watchdog.observers.api.EventEmitter", "watchdog.utils.BaseThread", "threading.Thread", "builtins.object"], "names": {".class": "SymbolTable", "__init__": {".class": "SymbolTableNode", "kind": "Mdef", "node": {".class": "FuncDef", "abstract_status": 0, "arg_kinds": [0, 0, 0, 1], "arg_names": ["self", "event_queue", "watch", "timeout"], "flags": [], "fullname": "watchdog.observers.read_directory_changes.WindowsApiEmitter.__init__", "name": "__init__", "type": null}}, "_handle": {".class": "SymbolTableNode", "implicit": true, "kind": "Mdef", "node": {".class": "Var", "flags": ["is_inferred"], "fullname": "watchdog.observers.read_directory_changes.WindowsApiEmitter._handle", "name": "_handle", "type": {".class": "AnyType", "missing_import_name": null, "source_any": null, "type_of_any": 1}}}, "_lock": {".class": "SymbolTableNode", "implicit": true, "kind": "Mdef", "node": {".class": "Var", "flags": ["is_inferred"], "fullname": "watchdog.observers.read_directory_changes.WindowsApiEmitter._lock", "name": "_lock", "type": {".class": "AnyType", "missing_import_name": null, "source_any": null, "type_of_any": 1}}}, "_read_events": {".class": "SymbolTableNode", "kind": "Mdef", "node": {".class": "FuncDef", "abstract_status": 0, "arg_kinds": [0], "arg_names": ["self"], "flags": [], "fullname": "watchdog.observers.read_directory_changes.WindowsApiEmitter._read_events", "name": "_read_events", "type": null}}, "on_thread_start": {".class": "SymbolTableNode", "kind": "Mdef", "node": {".class": "FuncDef", "abstract_status": 0, "arg_kinds": [0], "arg_names": ["self"], "flags": [], "fullname": "watchdog.observers.read_directory_changes.WindowsApiEmitter.on_thread_start", "name": "on_thread_start", "type": null}}, "on_thread_stop": {".class": "SymbolTableNode", "kind": "Mdef", "node": {".class": "FuncDef", "abstract_status": 0, "arg_kinds": [0], "arg_names": ["self"], "flags": [], "fullname": "watchdog.observers.read_directory_changes.WindowsApiEmitter.on_thread_stop", "name": "on_thread_stop", "type": null}}, "queue_events": {".class": "SymbolTableNode", "kind": "Mdef", "node": {".class": "FuncDef", "abstract_status": 0, "arg_kinds": [0, 0], "arg_names": ["self", "timeout"], "flags": [], "fullname": "watchdog.observers.read_directory_changes.WindowsApiEmitter.queue_events", "name": "queue_events", "type": null}}, "start": {".class": "SymbolTableNode", "kind": "Mdef", "node": {".class": "FuncDef", "abstract_status": 0, "arg_kinds": [0], "arg_names": ["self"], "flags": [], "fullname": "watchdog.observers.read_directory_changes.WindowsApiEmitter.start", "name": "start", "type": null}}}, "slots": null, "tuple_type": null, "type_vars": [], "typeddict_type": null}}, "WindowsApiObserver": {".class": "SymbolTableNode", "kind": "Gdef", "node": {".class": "TypeInfo", "_promote": [], "abstract_attributes": [], "bases": ["watchdog.observers.api.BaseObserver"], "declared_metaclass": null, "defn": {".class": "ClassDef", "fullname": "watchdog.observers.read_directory_changes.WindowsApiObserver", "name": "WindowsApiObserver", "type_vars": []}, "deletable_attributes": [], "flags": [], "fullname": "watchdog.observers.read_directory_changes.WindowsApiObserver", "has_param_spec_type": false, "metaclass_type": null, "metadata": {}, "module_name": "watchdog.observers.read_directory_changes", "mro": ["watchdog.observers.read_directory_changes.WindowsApiObserver", "watchdog.observers.api.BaseObserver", "watchdog.observers.api.EventDispatcher", "watchdog.utils.BaseThread", "threading.Thread", "builtins.object"], "names": {".class": "SymbolTable", "__init__": {".class": "SymbolTableNode", "kind": "Mdef", "node": {".class": "FuncDef", "abstract_status": 0, "arg_kinds": [0, 1], "arg_names": ["self", "timeout"], "flags": [], "fullname": "watchdog.observers.read_directory_changes.WindowsApiObserver.__init__", "name": "__init__", "type": null}}}, "slots": null, "tuple_type": null, "type_vars": [], "typeddict_type": null}}, "__annotations__": {".class": "SymbolTableNode", "kind": "Gdef", "node": {".class": "Var", "flags": ["is_ready"], "fullname": "watchdog.observers.read_directory_changes.__annotations__", "name": "__annotations__", "type": {".class": "Instance", "args": ["builtins.str", {".class": "AnyType", "missing_import_name": null, "source_any": null, "type_of_any": 6}], "type_ref": "builtins.dict"}}}, "__doc__": {".class": "SymbolTableNode", "kind": "Gdef", "node": {".class": "Var", "flags": ["is_ready"], "fullname": "watchdog.observers.read_directory_changes.__doc__", "name": "__doc__", "type": "builtins.str"}}, "__file__": {".class": "SymbolTableNode", "kind": "Gdef", "node": {".class": "Var", "flags": ["is_ready"], "fullname": "watchdog.observers.read_directory_changes.__file__", "name": "__file__", "type": "builtins.str"}}, "__name__": {".class": "SymbolTableNode", "kind": "Gdef", "node": {".class": "Var", "flags": ["is_ready"], "fullname": "watchdog.observers.read_directory_changes.__name__", "name": "__name__", "type": "builtins.str"}}, "__package__": {".class": "SymbolTableNode", "kind": "Gdef", "node": {".class": "Var", "flags": ["is_ready"], "fullname": "watchdog.observers.read_directory_changes.__package__", "name": "__package__", "type": "builtins.str"}}, "close_directory_handle": {".class": "SymbolTableNode", "cross_ref": "watchdog.observers.winapi.close_directory_handle", "kind": "Gdef"}, "generate_sub_created_events": {".class": "SymbolTableNode", "cross_ref": "watchdog.events.generate_sub_created_events", "kind": "Gdef"}, "generate_sub_moved_events": {".class": "SymbolTableNode", "cross_ref": "watchdog.events.generate_sub_moved_events", "kind": "Gdef"}, "get_directory_handle": {".class": "SymbolTableNode", "cross_ref": "watchdog.observers.winapi.get_directory_handle", "kind": "Gdef"}, "os": {".class": "SymbolTableNode", "cross_ref": "os", "kind": "Gdef"}, "platform": {".class": "SymbolTableNode", "cross_ref": "platform", "kind": "Gdef"}, "read_events": {".class": "SymbolTableNode", "cross_ref": "watchdog.observers.winapi.read_events", "kind": "Gdef"}, "threading": {".class": "SymbolTableNode", "cross_ref": "threading", "kind": "Gdef"}, "time": {".class": "SymbolTableNode", "cross_ref": "time", "kind": "Gdef"}}, "path": "C:\\Users\\zboehm\\scoop\\apps\\python\\current\\Lib\\site-packages\\watchdog\\observers\\read_directory_changes.py"}